nclutils/__init__.py
nclutils/constants.py
nclutils/py.typed
nclutils/fs/__init__.py
nclutils/fs/filesystem.py
nclutils/logging/__init__.py
nclutils/logging/logging.py
nclutils/network/__init__.py
nclutils/network/network.py
nclutils/pretty_print/__init__.py
nclutils/pretty_print/debug.py
nclutils/pretty_print/pretty_print.py
nclutils/pytest_fixtures/__init__.py
nclutils/pytest_fixtures/fixtures.py
nclutils/questions/__init__.py
nclutils/questions/questions.py
nclutils/sh/__init__.py
nclutils/sh/errors.py
nclutils/sh/shell_command.py
nclutils/strings/__init__.py
nclutils/strings/strings.py
nclutils/text_processing/__init__.py
nclutils/text_processing/text_processing.py
nclutils/utils/__init__.py
nclutils/utils/utils.py
nclutils-2.1.0.dist-info/METADATA
nclutils-2.1.0.dist-info/WHEEL
nclutils-2.1.0.dist-info/licenses/LICENSE
nclutils-2.1.0.dist-info/RECORD
