Metadata-Version: 2.4
Name: nclutils
Version: 2.1.0
Summary: Collection of convenience functions used in Python packages and scripts.
Author-email: Nathaniel Landau <github@natenate.org>
License-Expression: MIT
License-File: LICENSE
Classifier: Programming Language :: Python :: 3.10
Classifier: Programming Language :: Python :: 3.11
Classifier: Programming Language :: Python :: 3.12
Classifier: Programming Language :: Python :: 3.13
Requires-Python: >=3.10
Requires-Dist: loguru>=0.7.3
Requires-Dist: questionary>=2.1.0
Requires-Dist: rich>=14.1.0
Requires-Dist: sh>=2.2.2
